README.md
setup.py
auto_struct/__init__.py
auto_struct.egg-info/PKG-INFO
auto_struct.egg-info/SOURCES.txt
auto_struct.egg-info/dependency_links.txt
auto_struct.egg-info/not-zip-safe
auto_struct.egg-info/top_level.txt
auto_struct/data_types/__init__.py
auto_struct/data_types/array/__init__.py
auto_struct/data_types/array/array.py
auto_struct/data_types/array/uuid.py
auto_struct/data_types/base/__init__.py
auto_struct/data_types/base/base_single_value_type.py
auto_struct/data_types/base/base_struct.py
auto_struct/data_types/base/base_type.py
auto_struct/data_types/enums/__init__.py
auto_struct/data_types/enums/base_enum.py
auto_struct/data_types/enums/bitflags.py
auto_struct/data_types/int/__init__.py
auto_struct/data_types/int/integer.py
auto_struct/data_types/int/time.py
auto_struct/data_types/int/unsigned_integer.py
auto_struct/data_types/string/__init__.py
auto_struct/data_types/string/char.py
auto_struct/data_types/string/padding.py
auto_struct/data_types/string/string.py
auto_struct/exceptions/__init__.py
auto_struct/exceptions/base.py
auto_struct/exceptions/bitflag.py
auto_struct/exceptions/enum.py
auto_struct/exceptions/integer.py
auto_struct/exceptions/parsing.py
auto_struct/exceptions/struct.py
auto_struct/exceptions/type.py