Metadata-Version: 2.1
Name: auto-struct
Version: 0.700
Summary: Easily parse binary file in python3.8
Home-page: https://github.com/Valmarelox/auto_struct/tree/master
Author: efi
Author-email: valmarelox@gmail.com
License: MIT
Platform: UNKNOWN
Requires-Python: >=3.8
